{
    "static_33": [
        231
    ],
    "static_34": [
        231,
        830
    ],
    "static_35": [],
    "static_43": [
        208,
        229,
        292,
        367,
        414,
        427,
        464,
        570,
        598,
        799
    ],
    "static_44": [],
    "static_45": [],
    "static_53": [],
    "static_54": [],
    "static_55": [],
    "recycle_33": [
        9,
        10,
        11,
        12
    ],
    "recycle_34": [],
    "recycle_35": [],
    "recycle_43": [],
    "recycle_44": [],
    "recycle_45": [],
    "recycle_53": [],
    "recycle_54": [],
    "recycle_55": [],
    "xl_33": [
        265,
        271,
        332
    ],
    "xl_34": [],
    "xl_35": [],
    "xl_43": [],
    "xl_44": [],
    "xl_45": [],
    "xl_53": [],
    "xl_54": [],
    "xl_55": [],
    "xs_33": [
        1,
        6,
        9
    ],
    "xs_34": [
        2,
        5
    ],
    "xs_35": [
        1
    ],
    "xs_43": [
        1,
        4,
        8,
        13
    ],
    "xs_44": [],
    "xs_45": [],
    "xs_53": [],
    "xs_54": [],
    "xs_55": []
}